fbupkeep/__init__.py
fbupkeep/base.py
fbupkeep/runner.py
fbupkeep/tasks.py
fbupkeep-1.0.1.data/data/fbupkeep.cfg
fbupkeep-1.0.1.dist-info/LICENSE
fbupkeep-1.0.1.dist-info/METADATA
fbupkeep-1.0.1.dist-info/WHEEL
fbupkeep-1.0.1.dist-info/entry_points.txt
fbupkeep-1.0.1.dist-info/namespace_packages.txt
fbupkeep-1.0.1.dist-info/top_level.txt
fbupkeep-1.0.1.dist-info/RECORD
