Metadata-Version: 2.1
Name: fbupkeep
Version: 1.0.1
Summary: Firebird Upkeep utility
Home-page: https://github.com/pcisar/fbupkeep
Author: Pavel Císař
Author-email: pcisar@ibphoenix.cz
License: MIT
Project-URL: Source, https://github.com/pcisar/fbupkeep
Project-URL: Documentation, https://fbupkeep.rtfd.io/
Keywords: Firebird database backup maintenance
Platform: UNKNOWN
Classifier: Development Status :: 5 - Production/Stable
Classifier: Intended Audience :: System Administrators
Classifier: Intended Audience :: Developers
Classifier: License :: OSI Approved :: MIT License
Classifier: Programming Language :: Python :: 3
Classifier: Programming Language :: Python :: 3.5
Classifier: Programming Language :: Python :: 3.6
Classifier: Programming Language :: Python :: 3.7
Classifier: Operating System :: POSIX :: Linux
Classifier: Operating System :: Microsoft :: Windows
Classifier: Operating System :: MacOS
Classifier: Topic :: Database
Classifier: Topic :: System :: Archiving :: Backup
Classifier: Topic :: System :: Systems Administration
Classifier: Topic :: Utilities
Requires-Python: >=3.5, <4
Requires-Dist: fdb (>=2.0)
